cryptopay/__init__.py
cryptopay/admin.py
cryptopay/apps.py
cryptopay/forms.py
cryptopay/models.py
cryptopay/tests.py
cryptopay/urls.py
cryptopay/views.py
cryptopay/migrations/0001_initial.py
cryptopay/migrations/__init__.py
cryptopay/migrations/__pycache__/0001_initial.cpython-310.pyc
cryptopay/migrations/__pycache__/__init__.cpython-310.pyc
cryptopay/templates/cryptopay/payment_form.html
cryptopay/templates/cryptopay/success_page.html
django_cryptomus_test1-0.3.0.dist-info/METADATA
django_cryptomus_test1-0.3.0.dist-info/WHEEL
django_cryptomus_test1-0.3.0.dist-info/top_level.txt
django_cryptomus_test1-0.3.0.dist-info/RECORD
