Metadata-Version: 2.1
Name: django-cryptomus-test1
Version: 0.3.0
Summary: A Django app for integrating with Cryptomus payment gateway.
Home-page: https://github.com/rz-k/django_cryptomus
Author: reza karampour
Author-email: adamak.tng@gmail.com
License: MIT License
Classifier: Environment :: Web Environment
Classifier: Framework :: Django
Classifier: Framework :: Django :: 4.0
Classifier: Intended Audience :: Developers
Classifier: License :: OSI Approved :: MIT License
Classifier: Operating System :: OS Independent
Classifier: Programming Language :: Python
Classifier: Programming Language :: Python :: 3
Classifier: Programming Language :: Python :: 3.9
Classifier: Topic :: Internet :: WWW/HTTP
Classifier: Topic :: Internet :: WWW/HTTP :: Dynamic Content
Requires-Dist: Django >=4.0
